raggify_client/__init__.py
raggify_client/cli.py
raggify_client/client.py
raggify_client/config_manager.py
raggify_client/const.py
raggify_client/general_config.py
raggify_client/logger.py
raggify_client-0.3.8.dist-info/WHEEL
raggify_client-0.3.8.dist-info/entry_points.txt
raggify_client-0.3.8.dist-info/METADATA
raggify_client-0.3.8.dist-info/RECORD
