Metadata-Version: 2.3
Name: raggify-client
Version: 0.3.8
Summary: client tool for raggify, a llama index based library for building multimodal RAG systems
Keywords: rag,multimodal,embedding,cli,typer
Author: jun76
Author-email: jun76 <jun76.git@gmail.com>
License: MIT License
Classifier: Development Status :: 4 - Beta
Classifier: Intended Audience :: Developers
Classifier: Intended Audience :: System Administrators
Classifier: License :: OSI Approved :: MIT License
Classifier: Operating System :: OS Independent
Classifier: Programming Language :: Python :: 3
Classifier: Topic :: System :: Systems Administration
Classifier: Topic :: Utilities
Requires-Dist: mashumaro
Requires-Dist: python-dotenv
Requires-Dist: pyyaml
Requires-Dist: requests
Requires-Dist: typer
Requires-Python: >=3.10
Project-URL: Homepage, https://github.com/jun76/raggify
Project-URL: Issues, https://github.com/jun76/raggify/issues
